setup.py
robolab/Robolab.py
robolab/__init__.py
robolab.egg-info/PKG-INFO
robolab.egg-info/SOURCES.txt
robolab.egg-info/dependency_links.txt
robolab.egg-info/entry_points.txt
robolab.egg-info/top_level.txt